.gitignore
README.md
pyproject.toml
setup.cfg
setup.py
setupcmd.bat
setupcmd.sh
.github/workflows/push-tags-to-public.yml
.github/workflows/push-to-public.yml
.github/workflows/push-to-pypi.yml
demos/acquire_azurekinect.dgp
demos/playback_azurekinect.dgp
dgpython_azurekinect/__init__.py
dgpython_azurekinect/_version.py
dgpython_azurekinect/kinect.cpp
dgpython_azurekinect/kinect.pyx
dgpython_azurekinect.egg-info/PKG-INFO
dgpython_azurekinect.egg-info/SOURCES.txt
dgpython_azurekinect.egg-info/dependency_links.txt
dgpython_azurekinect.egg-info/not-zip-safe
dgpython_azurekinect.egg-info/top_level.txt