Metadata-Version: 2.2
Name: dgpython-azurekinect
Version: 0.2.0
Summary: Azure Kinect module for dgpython
Home-page: http://thermal.cnde.iastate.edu
Author: Stephen D. Holland
Classifier: Development Status :: 3 - Alpha
Classifier: License :: OSI Approved :: BSD License
Requires-Python: >=3.8
Dynamic: author
Dynamic: home-page
Dynamic: summary
